GPL.txt
LGPL.txt
LICENSE.md
MANIFEST.in
MIT_LICENSE.txt
setup.py
quick2wire/__init__.py
quick2wire/asm_generic_ioctl.py
quick2wire/board_revision.py
quick2wire/eventfd.py
quick2wire/gpio.py
quick2wire/i2c.py
quick2wire/i2c_ctypes.py
quick2wire/selector.py
quick2wire/spi.py
quick2wire/spi_ctypes.py
quick2wire/syscall.py
quick2wire/test_eventfd.py
quick2wire/test_gpio.py
quick2wire/test_gpio_loopback.py
quick2wire/test_selector.py
quick2wire/test_spi_loopback.py
quick2wire/test_timerfd.py
quick2wire/timerfd.py
quick2wire/parts/__init__.py
quick2wire/parts/mcp23017.py
quick2wire/parts/mcp23x17.py
quick2wire/parts/pcf8591.py
quick2wire/parts/test_mcp23017_interrupts_loopback.py
quick2wire/parts/test_mcp23017_loopback.py
quick2wire/parts/test_mcp23x17.py
quick2wire/parts/test_pcf8591.py
quick2wire/parts/test_pcf8591_loopback.py
quick2wire_peque.egg-info/PKG-INFO
quick2wire_peque.egg-info/SOURCES.txt
quick2wire_peque.egg-info/dependency_links.txt
quick2wire_peque.egg-info/top_level.txt