Metadata-Version: 1.1
Name: quick2wire-peque
Version: 0.0.1
Summary: Quick2Wire API for Physical Computing
Home-page: http://quick2wire.com
Author: Quick2Wire Ltd.
Author-email: info@quick2wire.com
License: LGPL or MIT
Platform: Linux
Classifier: Development Status :: 4 - Beta
Classifier: Environment :: Console
Classifier: Intended Audience :: Developers
Classifier: License :: OSI Approved :: GNU Lesser General Public License v3 (LGPLv3)
Classifier: License :: OSI Approved :: MIT License
Classifier: Programming Language :: Python
Classifier: Programming Language :: Python :: 3
Classifier: Natural Language :: English
Classifier: Topic :: Software Development
Provides: quick2wire
